odoo/addons/hr_timesheet_sheet_policy_project_manager/README.rst
odoo/addons/hr_timesheet_sheet_policy_project_manager/__init__.py
odoo/addons/hr_timesheet_sheet_policy_project_manager/__manifest__.py
odoo/addons/hr_timesheet_sheet_policy_project_manager/i18n/es.po
odoo/addons/hr_timesheet_sheet_policy_project_manager/i18n/hr_timesheet_sheet_policy_project_manager.pot
odoo/addons/hr_timesheet_sheet_policy_project_manager/i18n/it.po
odoo/addons/hr_timesheet_sheet_policy_project_manager/models/__init__.py
odoo/addons/hr_timesheet_sheet_policy_project_manager/models/account_analytic_line.py
odoo/addons/hr_timesheet_sheet_policy_project_manager/models/hr_timesheet_sheet.py
odoo/addons/hr_timesheet_sheet_policy_project_manager/models/res_company.py
odoo/addons/hr_timesheet_sheet_policy_project_manager/readme/CONTRIBUTORS.rst
odoo/addons/hr_timesheet_sheet_policy_project_manager/readme/DESCRIPTION.rst
odoo/addons/hr_timesheet_sheet_policy_project_manager/static/description/icon.png
odoo/addons/hr_timesheet_sheet_policy_project_manager/static/description/index.html
odoo/addons/hr_timesheet_sheet_policy_project_manager/tests/__init__.py
odoo/addons/hr_timesheet_sheet_policy_project_manager/tests/test_hr_timesheet_sheet_policy_project_manager.py
odoo/addons/hr_timesheet_sheet_policy_project_manager/views/hr_timesheet_sheet.xml
odoo14_addon_hr_timesheet_sheet_policy_project_manager-14.0.1.0.1.dev7.dist-info/METADATA
odoo14_addon_hr_timesheet_sheet_policy_project_manager-14.0.1.0.1.dev7.dist-info/WHEEL
odoo14_addon_hr_timesheet_sheet_policy_project_manager-14.0.1.0.1.dev7.dist-info/top_level.txt
odoo14_addon_hr_timesheet_sheet_policy_project_manager-14.0.1.0.1.dev7.dist-info/RECORD
